A1/Q5/half_adder.v
// METADATA ABOUT THE PROGRAM
//
// 	AUTHORS: Nisarg S. Joshi and Yash M. Agarwal
// 	REG NO:  171CO226	     171CO253
// 	MODULE:  half_adder
// 	DATE:	 14th Oct 2018
//
// END META DATA

module half_adder(ip1,ip2,sum,carry);

	// Mapping input and output pins
	input ip1, ip2;
	output sum, carry;

	// Implementing the boolean function for Half adder.
	// sum = ip1 xor ip2
	// carry = ip1 and ip2
	xor(sum,ip1,ip2);
	and(carry,ip1,ip2);

endmodule

A1/Q4/full_adder.v
// METADATA ABOUT THE MODULE
//
// 	AUTHORS: Nisarg S. Joshi and Yash M. Agarwal
// 	REG NO:  171CO226	     171CO253
// 	MODULE:  full_adder
// 	DATE:	 14th Oct 2018
//
// END META DATA

module full_adder(ip1,ip2,c_in,sum,c_out);

	input ip1,ip2,c_in;
	output sum,c_out;
	wire r1,r2,r3;

	// r2 = carry of h1, r1 = sum of h1
	// r3 = carry of h2
	half_adder h1(ip1,ip2,r1,r2);
	half_adder h2(r1,c_in,sum,r3);

	or(c_out,r2,r3);

endmodule

A1/Q4/test_full_adder.v
// METADATA ABOUT THE MODULE
//
// 	AUTHORS: Nisarg S. Joshi and Yash M. Agarwal
// 	REG NO:  171CO226	     171CO253
// 	MODULE:  test_full_adder
// 	DATE:	 14th Oct 2018
//
// END META DATA

`timescale 1ns/1ns

module test;

	// Declaring the input and output
	wire sum,c_out;
	reg ip1,ip2,c_in;

	// Creating the instance of the full_adder module and passing the input and output
	full_adder fa(ip1,ip2,c_in,sum,c_out);


	initial 
		begin 
			$dumpfile("full_adder.vcd");
			$dumpvars(0,test);
		end

	// Initial block to update the values of the input every 20 units(20 ns)
	initial
		begin
			ip1=1'b0;
			ip2=1'b0;
			c_in=1'b0;
		#20;
			ip1=1'b0;
			ip2=1'b0;
			c_in=1'b1;
		#20;
			ip1=1'b0;
			ip2=1'b1;
			c_in=1'b0;
		#20;
			ip1=1'b0;
			ip2=1'b1;
			c_in=1'b1;
		#20;
			ip1=1'b1;
			ip2=1'b0;
			c_in=1'b0;
		#20;
			ip1=1'b1;
			ip2=1'b0;
			c_in=1'b1;
		#20;
			ip1=1'b1;
			ip2=1'b1;
			c_in=1'b0;
		#20;
			ip1=1'b1;
			ip2=1'b1;
			c_in=1'b1;
		#20;
		end

	// Outputting the values. Ends after 160 units (160ns)	
	initial
		begin
			$monitor("Time=%0d ip1=%b ip2=%b c_in=%b sum=%b carry=%b",$time,ip1,ip2,c_in,sum,c_out);
			#160 $finish;
		end

endmodule

A1/Q4/full_adder.vcd
$date
	Sun Oct 14 17:52:52 2018
$end
$version
	Icarus Verilog
$end
$timescale
	1ns
$end
$scope module test $end
$var wire 1 ! c_out $end
$var wire 1 " sum $end
$var reg 1 # c_in $end
$var reg 1 $ ip1 $end
$var reg 1 % ip2 $end
$scope module fa $end
$var wire 1 & c_in $end
$var wire 1 ! c_out $end
$var wire 1 ' ip1 $end
$var wire 1 ( ip2 $end
$var wire 1 ) r1 $end
$var wire 1 * r2 $end
$var wire 1 + r3 $end
$var wire 1 " sum $end
$scope module h1 $end
$var wire 1 * carry $end
$var wire 1 ' ip1 $end
$var wire 1 ( ip2 $end
$var wire 1 ) sum $end
$upscope $end
$scope module h2 $end
$var wire 1 + carry $end
$var wire 1 ) ip1 $end
$var wire 1 & ip2 $end
$var wire 1 " sum $end
$upscope $end
$upscope $end
$upscope $end
$enddefinitions $end
#0
$dumpvars
0+
0*
0)
0(
0'
0&
0%
0$
0#
0"
0!
$end
#20
1"
1#
1&
#40
1)
0#
0&
1%
1(
#60
1!
0"
1+
1#
1&
#80
0!
1"
0+
0#
0&
0%
0(
1$
1'
#100
1!
0"
1+
1#
1&
#120
0+
0)
1*
0#
0&
1%
1(
#140
1"
1#
1&
