A1/Q2/decoder.v
// METADATA ABOUT THE MODULE
//
//     AUTHORS: Nisarg S. Joshi and Yash M. Agarwal
//     REG NO:  171CO226         171CO253
//     MODULE:  decoder
//     DATE:   14th Oct 2018
//
// END META DATA

module decoder(ip,op,en);

       input [3:0]ip;              // Declaring the input pins and output pins along with the range of bits
       output [15:0]op;
       input en;

       // Assigning the values to the output bits based on the boolean logic for decoder
       assign op[0] = ~ip[3] & ~ip[2] & ~ip[1] & ~ip[0]  & en,
              op[1] = ~ip[3] & ~ip[2] & ~ip[1] &  ip[0]  & en,
              op[2] = ~ip[3] & ~ip[2] &  ip[1] & ~ip[0]  & en,
              op[3] = ~ip[3] & ~ip[2] &  ip[1] &  ip[0]  & en,
              op[4] = ~ip[3] &  ip[2] & ~ip[1] & ~ip[0]  & en,
              op[5] = ~ip[3] &  ip[2] & ~ip[1] &  ip[0]  & en,
              op[6] = ~ip[3] &  ip[2] &  ip[1] & ~ip[0]  & en,
              op[7] = ~ip[3] &  ip[2] &  ip[1] &  ip[0]  & en,
              op[8] =  ip[3] & ~ip[2] & ~ip[1] & ~ip[0]  & en,
              op[9] =  ip[3] & ~ip[2] & ~ip[1] &  ip[0]  & en,
              op[10] = ip[3] & ~ip[2] &  ip[1] & ~ip[0]  & en,
              op[11] = ip[3] & ~ip[2] &  ip[1] &  ip[0]  & en,
              op[12] = ip[3] &  ip[2] & ~ip[1] & ~ip[0]  & en,
              op[13] = ip[3] &  ip[2] & ~ip[1] &  ip[0]  & en,
              op[14] = ip[3] &  ip[2] &  ip[1] & ~ip[0]  & en,
              op[15] = ip[3] &  ip[2] &  ip[1] &  ip[0]  & en;

endmodule

A1/Q2/test_decoder.v
// METADATA ABOUT THE MODULE
//
// 	AUTHORS: Nisarg S. Joshi and Yash M. Agarwal
// 	REG NO:  171CO226	     171CO253
// 	MODULE:  test_decoder
// 	DATE:	 14th Oct 2018
//
// END META DATA

`timescale 1ns/1ns

module test;

	// Declaring the wires and registers to store values of input and output to be passed in the decoder instance
	wire [15:0]op;
	reg [3:0]ip;
	reg en;

	// Calling the decoder instance passing the above inputs and outputs
	decoder dec(ip,op,en);

	// vcd file for gtkwave
	initial 
		begin
			$dumpfile("decoder.vcd");
			$dumpvars(0,test);
		end

	// Generating the input values to be fed to the decoder instance
	initial 
		begin
			en=1'b1;
			for(ip=0;ip<=15;ip=ip+1)
			#20;		// Delay of 20 units(1ns) in every increment of input value
		end

	// Printing the output to the screen
	initial 
		begin
			$monitor("Input=%b%b%b%b || Output=%b%b%b%b%b%b%b%b%b%b%b%b%b%b%b%b", ip[3],ip[2],ip[1],ip[0], op[15],op[14],op[13],op[12],op[11],op[10],op[9],op[8],op[7],op[6],op[5],op[4],op[3],op[2],op[1],op[0]);
			#300 $finish;		// Based on the delay set above, total time to exit the program is 300 units (ns)
		end

endmodule

Q2/decoder.vcd
$date
	Sun Oct 14 17:28:46 2018
$end
$version
	Icarus Verilog
$end
$timescale
	1ns
$end
$scope module test $end
$var wire 16 ! op [15:0] $end
$var reg 1 " en $end
$var reg 4 # ip [3:0] $end
$scope module dec $end
$var wire 1 $ en $end
$var wire 4 % ip [3:0] $end
$var wire 16 & op [15:0] $end
$upscope $end
$upscope $end
$enddefinitions $end
#0
$dumpvars
b1 &
b0 %
1$
b0 #
1"
b1 !
$end
#20
b10 !
b10 &
b1 #
b1 %
#40
b100 !
b100 &
b10 #
b10 %
#60
b1000 !
b1000 &
b11 #
b11 %
#80
b10000 !
b10000 &
b100 #
b100 %
#100
b100000 !
b100000 &
b101 #
b101 %
#120
b1000000 !
b1000000 &
b110 #
b110 %
#140
b10000000 !
b10000000 &
b111 #
b111 %
#160
b100000000 !
b100000000 &
b1000 #
b1000 %
#180
b1000000000 !
b1000000000 &
b1001 #
b1001 %
#200
b10000000000 !
b10000000000 &
b1010 #
b1010 %
#220
b100000000000 !
b100000000000 &
b1011 #
b1011 %
#240
b1000000000000 !
b1000000000000 &
b1100 #
b1100 %
#260
b10000000000000 !
b10000000000000 &
b1101 #
b1101 %
#280
b100000000000000 !
b100000000000000 &
b1110 #
b1110 %
#300
b1000000000000000 !
b1000000000000000 &
b1111 #
b1111 %
