Q2/encoder.v
// METADATA ABOUT THE MODULE
//
// 	AUTHORS: Nisarg S. Joshi and Yash M. Agarwal
// 	REG NO:  171CO226	     171CO253
// 	MODULE:  encoder
// 	DATE:	 14th Oct 2018
//
// END META DATA

module encoder(ip,en,op);
	
	// Declaring the inputs and outputs
	input [15:0]ip;
	input en;
	output [3:0]op;

	// Declaring the wires for internal usage
	wire r1,r2,r3,r4;

	// Storing the intermediate values in wires based on the boolean function for encoder
	or (r1,ip[8],ip[9],ip[10],ip[11],ip[12],ip[13],ip[14],ip[15]),
	   (r2,ip[4],ip[5],ip[6],ip[7],ip[12],ip[13],ip[14],ip[15]),
	   (r3,ip[2],ip[3],ip[6],ip[7],ip[10],ip[11],ip[14],ip[15]),
	   (r4,ip[1],ip[3],ip[5],ip[7],ip[9],ip[11],ip[13],ip[15]);

	// Putting the final values in output using the boolean function
	and (op[3],r1,en),
	    (op[2],r2,en),
	    (op[1],r3,en),
	    (op[0],r4,en);

endmodule

Q2/test_encoder.v
// METADATA ABOUT THE MODULE
//
// 	AUTHORS: Nisarg S. Joshi and Yash M. Agarwal
// 	REG NO:  171CO226	     171CO253
// 	MODULE:  test_encoder
// 	DATE:	 14th Oct 2018
//
// END META DATA

`timescale 1ns/1ns

module test;

	// Init input and output values
	wire [3:0]op;
	reg [15:0]ip;
	reg en;

	// Instance of the encoder module, passing the input and output
	encoder enc(ip,en,op);
	integer i;

	initial 
		begin
			$dumpfile("encoder.vcd");
			$dumpvars(0,test);
		end

	initial 
		begin
			// Putting enable = 1
			en=1'b1;
			// Generating the input values
			for(i=0;i<=15;i=i+1)
			 	begin
			 		ip=0;
				 	ip[i]=1;
			 		#20;
			 	end
		end

	initial 
		begin              
			//displaying Output values
			$monitor("input=%b%b%b%b%b%b%b%b%b%b%b%b%b%b%b%b || output=%b%b%b%b",ip[15],ip[14],ip[13],ip[12],ip[11],ip[10],ip[9],ip[8],ip[7],ip[6],ip[5],ip[4],ip[3],ip[2],ip[1],ip[0],op[3],op[2],op[1],op[0]);
			#300 $finish;
		end
endmodule

Q2/encoder.vcd
$date
	Sun Oct 14 17:27:27 2018
$end
$version
	Icarus Verilog
$end
$timescale
	1ns
$end
$scope module test $end
$var wire 4 ! op [3:0] $end
$var reg 1 " en $end
$var integer 32 # i [31:0] $end
$var reg 16 $ ip [15:0] $end
$scope module enc $end
$var wire 1 % en $end
$var wire 16 & ip [15:0] $end
$var wire 4 ' op [3:0] $end
$var wire 1 ( r1 $end
$var wire 1 ) r2 $end
$var wire 1 * r3 $end
$var wire 1 + r4 $end
$upscope $end
$upscope $end
$enddefinitions $end
#0
$dumpvars
0+
0*
0)
0(
b0 '
b1 &
1%
b1 $
b0 #
1"
b0 !
$end
#20
b1 !
b1 '
1+
b10 $
b10 &
b1 #
#40
b10 !
b10 '
1*
0+
b100 $
b100 &
b10 #
#60
b11 !
b11 '
1+
b1000 $
b1000 &
b11 #
#80
b100 !
b100 '
1)
0*
0+
b10000 $
b10000 &
b100 #
#100
b101 !
b101 '
1+
b100000 $
b100000 &
b101 #
#120
b110 !
b110 '
1*
0+
b1000000 $
b1000000 &
b110 #
#140
b111 !
b111 '
1+
b10000000 $
b10000000 &
b111 #
#160
b1000 !
b1000 '
1(
0)
0*
0+
b100000000 $
b100000000 &
b1000 #
#180
b1001 !
b1001 '
1+
b1000000000 $
b1000000000 &
b1001 #
#200
b1010 !
b1010 '
1*
0+
b10000000000 $
b10000000000 &
b1010 #
#220
b1011 !
b1011 '
1+
b100000000000 $
b100000000000 &
b1011 #
#240
b1100 !
b1100 '
1)
0*
0+
b1000000000000 $
b1000000000000 &
b1100 #
#260
b1101 !
b1101 '
1+
b10000000000000 $
b10000000000000 &
b1101 #
#280
b1110 !
b1110 '
1*
0+
b100000000000000 $
b100000000000000 &
b1110 #
#300
b1111 !
b1111 '
1+
b1000000000000000 $
b1000000000000000 &
b1111 #
